ska_pss_protest/__init__.py
ska_pss_protest/_config.py
ska_pss_protest/candidate.py
ska_pss_protest/candlist.py
ska_pss_protest/conftest.py
ska_pss_protest/fil.py
ska_pss_protest/logparser.py
ska_pss_protest/pipeline.py
ska_pss_protest/pytest.ini
ska_pss_protest/requester.py
ska_pss_protest/test_ingest_export.py
ska_pss_protest/test_sps_emulator.py
ska_pss_protest/data/config_templates/ingest_export.xml
ska_pss_protest/data/config_templates/sps_pipeline_config_no_export.xml
ska_pss_protest/features/ingest_export.feature
ska_pss_protest/features/sps_emulator.feature
ska_pss_protest-0.0.1.data/scripts/protest
ska_pss_protest-0.0.1.dist-info/LICENSE
ska_pss_protest-0.0.1.dist-info/METADATA
ska_pss_protest-0.0.1.dist-info/WHEEL
ska_pss_protest-0.0.1.dist-info/top_level.txt
ska_pss_protest-0.0.1.dist-info/RECORD
