Metadata-Version: 2.1
Name: ska-pss-protest
Version: 0.0.1
Summary: SKA PSS Product Testing Framework
Home-page: https://gitlab.com/ska-telescope/pss/ska-pss-protest
Author: Benjamin Shaw, Lina Levin Preston
Author-email: benjamin.shaw@manchester.ac.uk, lina.preston@manchester.ac.uk
License: BSD 2-clause
Platform: UNKNOWN
Classifier: Programming Language :: Python :: 3.6
Requires-Dist: numpy
Requires-Dist: requests
Requires-Dist: pytest-mock
Requires-Dist: pytest-html
Requires-Dist: pytest-repeat
Requires-Dist: pytest-bdd
Requires-Dist: pytest
Provides-Extra: dev
Requires-Dist: black ; extra == 'dev'
Requires-Dist: isort ; extra == 'dev'
Requires-Dist: flake8 ; extra == 'dev'
Requires-Dist: pylint ; extra == 'dev'
Requires-Dist: pylint-junit ; extra == 'dev'
